README.md
setup.cfg
setup.py
auspostgen/__init__.py
auspostgen/auspost.so
auspostgen.egg-info/PKG-INFO
auspostgen.egg-info/SOURCES.txt
auspostgen.egg-info/dependency_links.txt
auspostgen.egg-info/entry_points.txt
auspostgen.egg-info/requires.txt
auspostgen.egg-info/top_level.txt