Metadata-Version: 2.1
Name: auspostgen
Version: 0.0.2
Summary: Generation of the Australia Post Barcode versions 37, 52, 67
Home-page: https://github.com/damiandennis/auspost
Author: Damian Dennis
Author-email: damiandennis@gmail.com
License: UNKNOWN
Platform: UNKNOWN
Requires-Python: >=3.6
